[{"wort":"Avancen"},{"wort":"avanciere"},{"wort":"avancieren"},{"wort":"avancierend"},{"wort":"avancierende"},{"wort":"avancierendem"},{"wort":"avancierenden"},{"wort":"avancierender"},{"wort":"avancierendes"},{"wort":"Avancierens"},{"wort":"avancierst"},{"wort":"avanciert"},{"wort":"avancierte"},{"wort":"avanciertem"},{"wort":"avancierten"},{"wort":"avancierter"},{"wort":"avanciertes"},{"wort":"avanciertest"},{"wort":"avanciertet"},{"wort":"Avantgarde"},{"wort":"Avantgardeanspruch"},{"wort":"Avantgardeanspruchs"},{"wort":"Avantgardearchitekt"},{"wort":"Avantgardearchitektin"},{"wort":"Avantgardearchitektur"},{"wort":"Avantgardebewegung"},{"wort":"Avantgardebewegungen"},{"wort":"Avantgardeeinheit"},{"wort":"Avantgardeeinheiten"},{"wort":"Avantgardefestival"},{"wort":"Avantgardefestivals"},{"wort":"Avantgardefilm"},{"wort":"Avantgardefilmchen"},{"wort":"Avantgardefilmchens"},{"wort":"Avantgardefilme"},{"wort":"Avantgardefilmen"},{"wort":"Avantgardefilmer"},{"wort":"Avantgardefilmerin"},{"wort":"Avantgardefilmern"},{"wort":"Avantgardefilmers"},{"wort":"Avantgardefilms"},{"wort":"Avantgardefunktion"},{"wort":"Avantgardefunktionen"},{"wort":"Avantgardegenre"},{"wort":"Avantgardegenres"},{"wort":"Avantgardegruppe"},{"wort":"Avantgardegruppen"},{"wort":"Avantgardekino"},{"wort":"Avantgardekinos"},{"wort":"Avantgardekomponist"},{"wort":"Avantgardekomponisten"},{"wort":"Avantgardekomponistin"},{"wort":"Avantgardekunst"},{"wort":"Avantgardekunstrichtung"},{"wort":"Avantgardekunstrichtungen"},{"wort":"Avantgardeleistung"},{"wort":"Avantgardeleistungen"},{"wort":"Avantgardeliteratur"},{"wort":"Avantgardeliteraturen"},{"wort":"Avantgardelokal"},{"wort":"Avantgardelokale"},{"wort":"Avantgardelokalen"},{"wort":"Avantgardelokals"},{"wort":"Avantgardemaler"},{"wort":"Avantgardemalerin"},{"wort":"Avantgardemalern"},{"wort":"Avantgardemalers"},{"wort":"Avantgardemusik"},{"wort":"Avantgardemusiker"},{"wort":"Avantgardemusikerin"},{"wort":"Avantgardemusikerinnen"},{"wort":"Avantgardemusikern"},{"wort":"Avantgardemusikers"},{"wort":"Avantgarden"},{"wort":"Avantgardepart"},{"wort":"Avantgardepartei"},{"wort":"Avantgardeparteien"},{"wort":"Avantgardeparts"},{"wort":"Avantgarderegiment"},{"wort":"Avantgarderegisseur"},{"wort":"Avantgarderegisseure"},{"wort":"Avantgarderegisseuren"},{"wort":"Avantgarderegisseurin"},{"wort":"Avantgarderegisseurs"},{"wort":"Avantgardeszene"},{"wort":"Avantgardetheater"},{"wort":"Avantgardetheaters"},{"wort":"Avantgardezeitschrift"},{"wort":"Avantgardezeitschriften"},{"wort":"Avantgardismus"},{"wort":"Avantgardist"},{"wort":"Avantgardisten"},{"wort":"Avantgardistin"},{"wort":"avantgardistisch"},{"wort":"avantgardistische"},{"wort":"avantgardistischem"},{"wort":"avantgardistischen"},{"wort":"avantgardistischer"},{"wort":"avantgardistischere"},{"wort":"avantgardistischerem"},{"wort":"avantgardistischeren"},{"wort":"avantgardistischerer"},{"wort":"avantgardistischeres"},{"wort":"avantgardistisches"},{"wort":"avantgardistischste"},{"wort":"avantgardistischstem"},{"wort":"avantgardistischsten"},{"wort":"avantgardistischster"},{"wort":"avantgardistischstes"},{"wort":"avanti"},{"wort":"Avatar"},{"wort":"Avatare"},{"wort":"Avataren"},{"wort":"Avatars"},{"wort":"Avenue"},{"wort":"Avenuen"},{"wort":"Averroës"},{"wort":"avers"},{"wort":"averse"},{"wort":"aversem"},{"wort":"aversen"},{"wort":"averser"},{"wort":"averses"},{"wort":"Aversion"},{"wort":"Aversionen"},{"wort":"Aviatik"},{"wort":"Aviatiker"},{"wort":"Aviatikerin"},{"wort":"Aviatikerinnen"},{"wort":"Aviatikern"},{"wort":"Aviatikers"},{"wort":"Avicenna"},{"wort":"Avicennas"},{"wort":"Avifauna"},{"wort":"Avignon"},{"wort":"Avignons"},{"wort":"Avionik"},{"wort":"Avis"},{"wort":"avisiere"},{"wort":"avisieren"},{"wort":"avisierend"},{"wort":"avisierende"},{"wort":"avisierendem"},{"wort":"avisierenden"},{"wort":"avisierender"},{"wort":"avisierendes"},{"wort":"Avisierens"},{"wort":"avisierst"},{"wort":"avisiert"},{"wort":"avisierte"},{"wort":"avisiertem"},{"wort":"avisierten"},{"wort":"avisierter"},{"wort":"avisiertes"},{"wort":"avisiertest"},{"wort":"avisiertet"},{"wort":"Aviso"},{"wort":"Aviv"},{"wort":"Avivs"},{"wort":"Avocado"},{"wort":"Avocadokern"},{"wort":"Avocadokerne"},{"wort":"Avocadokernen"},{"wort":"Avocadokerns"},{"wort":"Avocados"},{"wort":"Avogadro"},{"wort":"Avogadros"},{"wort":"Avus"}]