[{"wort":"vögel"},{"wort":"Vögel"},{"wort":"Vögelchen"},{"wort":"Vögelchens"},{"wort":"vögele"},{"wort":"Vögelei"},{"wort":"vögeln"},{"wort":"Vögeln"},{"wort":"vögelnd"},{"wort":"vögelnde"},{"wort":"vögelndem"},{"wort":"vögelnden"},{"wort":"vögelnder"},{"wort":"vögelndes"},{"wort":"Vögelns"},{"wort":"vögelst"},{"wort":"vögelt"},{"wort":"vögelte"},{"wort":"vögelten"},{"wort":"vögeltest"},{"wort":"vögeltet"},{"wort":"vögle"},{"wort":"Vöglein"},{"wort":"Vögleins"},{"wort":"Vögte"},{"wort":"Vögten"},{"wort":"Völkchen"},{"wort":"Völker"},{"wort":"Völkerapostel"},{"wort":"Völkeraposteln"},{"wort":"Völkerapostels"},{"wort":"Völkeraufstand"},{"wort":"Völkerball"},{"wort":"Völkerballs"},{"wort":"Völkerbefreiung"},{"wort":"Völkerbefreiungen"},{"wort":"Völkerbegegnung"},{"wort":"Völkerbegegnungen"},{"wort":"Völkerbeschreibung"},{"wort":"Völkerbeschreibungen"},{"wort":"Völkerbewegung"},{"wort":"Völkerbewegungen"},{"wort":"Völkerbezeichnung"},{"wort":"Völkerbezeichnungen"},{"wort":"Völkerbeziehung"},{"wort":"Völkerbeziehungen"},{"wort":"Völkerbildung"},{"wort":"Völkerbildungen"},{"wort":"Völkerbiologie"},{"wort":"Völkerbuch"},{"wort":"Völkerbücher"},{"wort":"Völkerbüchern"},{"wort":"Völkerbuches"},{"wort":"Völkerbuchs"},{"wort":"Völkerbund"},{"wort":"Völkerbundes"},{"wort":"Völkerbundmandat"},{"wort":"Völkerbundmandate"},{"wort":"Völkerbundmandaten"},{"wort":"Völkerbundmandats"},{"wort":"Völkerchaos"},{"wort":"Völkerdiebstahl"},{"wort":"Völkerfamilie"},{"wort":"Völkerfamilien"},{"wort":"Völkerfeindschaft"},{"wort":"Völkerfeindschaften"},{"wort":"Völkerfreundschaft"},{"wort":"Völkerfreundschaften"},{"wort":"Völkerfriede"},{"wort":"Völkerfrieden"},{"wort":"Völkerfriedens"},{"wort":"Völkerfrühling"},{"wort":"Völkerfrühlings"},{"wort":"Völkergalerie"},{"wort":"Völkergalerien"},{"wort":"Völkergebilde"},{"wort":"Völkergebilden"},{"wort":"Völkergebildes"},{"wort":"Völkergeist"},{"wort":"Völkergeistes"},{"wort":"Völkergemeinschaft"},{"wort":"Völkergemeinschaften"},{"wort":"Völkergemisch"},{"wort":"Völkergemische"},{"wort":"Völkergemischen"},{"wort":"Völkergemisches"},{"wort":"Völkergemischs"},{"wort":"Völkergericht"},{"wort":"Völkergerichte"},{"wort":"Völkergerichten"},{"wort":"Völkergerichtes"},{"wort":"Völkergerichts"},{"wort":"Völkergeschichte"},{"wort":"Völkergeschichten"},{"wort":"Völkergewohnheitsrecht"},{"wort":"Völkergewohnheitsrechte"},{"wort":"Völkergewohnheitsrechten"},{"wort":"Völkergewohnheitsrechts"},{"wort":"Völkergruppe"},{"wort":"Völkergruppen"},{"wort":"Völkerhass"},{"wort":"Völkerhasses"},{"wort":"Völkerkreis"},{"wort":"Völkerkreise"},{"wort":"Völkerkreisen"},{"wort":"Völkerkreises"},{"wort":"Völkerkrieg"},{"wort":"Völkerkriege"},{"wort":"Völkerkriegen"},{"wort":"Völkerkriegs"},{"wort":"Völkerkunde"},{"wort":"Völkerkundemuseen"},{"wort":"Völkerkundemuseum"},{"wort":"Völkerkundemuseums"},{"wort":"Völkerkundler"},{"wort":"Völkerkundlerin"},{"wort":"Völkerkundlerinnen"},{"wort":"Völkerkundlern"},{"wort":"Völkerkundlers"},{"wort":"völkerkundlich"},{"wort":"völkerkundliche"},{"wort":"völkerkundlichem"},{"wort":"völkerkundlichen"},{"wort":"völkerkundlicher"},{"wort":"völkerkundliches"},{"wort":"Völkerleben"},{"wort":"Völkerlebens"},{"wort":"Völkermanifest"},{"wort":"Völkermanifeste"},{"wort":"Völkermanifesten"},{"wort":"Völkermanifestes"},{"wort":"Völkermarkt"},{"wort":"Völkermärkte"},{"wort":"Völkermärkten"},{"wort":"Völkermarktes"},{"wort":"Völkermassen"},{"wort":"Völkermission"},{"wort":"Völkermissionen"},{"wort":"Völkermord"},{"wort":"Völkermordartikel"},{"wort":"Völkermordartikeln"},{"wort":"Völkermordartikels"},{"wort":"Völkermorddiskussion"},{"wort":"Völkermorddiskussionen"},{"wort":"Völkermorde"},{"wort":"Völkermorden"},{"wort":"Völkermörder"},{"wort":"Völkermordereignis"},{"wort":"Völkermordereignisse"},{"wort":"Völkermordereignissen"},{"wort":"Völkermordereignisses"},{"wort":"Völkermördern"},{"wort":"Völkermörders"},{"wort":"Völkermordes"},{"wort":"Völkermordforschung"},{"wort":"Völkermordforschungen"},{"wort":"Völkermordkonvention"},{"wort":"Völkermordkonventionen"},{"wort":"Völkermordpropaganda"},{"wort":"Völkermords"},{"wort":"Völkermordtatbestand"},{"wort":"Völkermordtatbestände"},{"wort":"Völkermordtatbeständen"},{"wort":"Völkermordtatbestandes"},{"wort":"Völkermordtatbestands"},{"wort":"Völkermordzentrale"},{"wort":"Völkermordzentralen"},{"wort":"Völkern"},{"wort":"Völkername"},{"wort":"Völkerorakel"},{"wort":"Völkerorakeln"},{"wort":"Völkerorakels"},{"wort":"Völkerpsychologe"},{"wort":"Völkerpsychologen"},{"wort":"Völkerpsychologie"},{"wort":"Völkerpsychologin"},{"wort":"Völkerpsychologinnen"},{"wort":"Völkerrecht"},{"wort":"Völkerrechte"},{"wort":"Völkerrechten"},{"wort":"Völkerrechtes"},{"wort":"Völkerrechtler"},{"wort":"Völkerrechtlerin"},{"wort":"Völkerrechtlern"},{"wort":"Völkerrechtlers"},{"wort":"völkerrechtlich"},{"wort":"völkerrechtliche"},{"wort":"völkerrechtlichem"},{"wort":"völkerrechtlichen"},{"wort":"völkerrechtlicher"},{"wort":"völkerrechtliches"},{"wort":"Völkerrechts"},{"wort":"Völkerrechtsbüro"},{"wort":"Völkerrechtsbüros"},{"wort":"Völkerrechtsdekade"},{"wort":"Völkerrechtsdekaden"},{"wort":"Völkerrechtsdirektion"},{"wort":"Völkerrechtsdirektionen"},{"wort":"Völkerrechtsdiskussion"},{"wort":"Völkerrechtsdiskussionen"},{"wort":"Völkerrechtsdoktrin"},{"wort":"Völkerrechtsdoktrinen"},{"wort":"Völkerrechtsexperte"},{"wort":"Völkerrechtsexperten"},{"wort":"Völkerrechtsexpertin"},{"wort":"Völkerrechtsexpertinnen"},{"wort":"Völkerrechtsfähigkeit"},{"wort":"Völkerrechtsfähigkeiten"},{"wort":"Völkerrechtsgemeinschaft"},{"wort":"Völkerrechtsgemeinschaften"},{"wort":"Völkerrechtsgerichtsbarkeit"},{"wort":"Völkerrechtsgeschichte"},{"wort":"Völkerrechtsgeschichten"},{"wort":"Völkerrechtsgesetz"},{"wort":"Völkerrechtsgesetze"},{"wort":"Völkerrechtsgesetzen"},{"wort":"Völkerrechtsgesetzes"},{"wort":"Völkerrechtskenner"},{"wort":"Völkerrechtskennern"},{"wort":"Völkerrechtskenners"},{"wort":"Völkerrechtskommission"},{"wort":"Völkerrechtskommissionen"},{"wort":"völkerrechtskonform"},{"wort":"völkerrechtskonforme"},{"wort":"völkerrechtskonformem"},{"wort":"völkerrechtskonformen"},{"wort":"völkerrechtskonformer"},{"wort":"völkerrechtskonformes"},{"wort":"Völkerrechtskonzeption"},{"wort":"Völkerrechtskonzeptionen"},{"wort":"Völkerrechtslehre"},{"wort":"Völkerrechtslehren"},{"wort":"Völkerrechtslehrer"},{"wort":"Völkerrechtslehrerin"},{"wort":"Völkerrechtslehrern"},{"wort":"Völkerrechtslehrers"},{"wort":"Völkerrechtsnorm"},{"wort":"Völkerrechtsnormen"},{"wort":"Völkerrechtsobjekt"},{"wort":"Völkerrechtsobjekte"},{"wort":"Völkerrechtsobjekten"},{"wort":"Völkerrechtsobjektes"},{"wort":"Völkerrechtsordnung"},{"wort":"Völkerrechtsordnungen"},{"wort":"Völkerrechtspersönlichkeit"},{"wort":"Völkerrechtspersönlichkeiten"},{"wort":"Völkerrechtspraxis"},{"wort":"Völkerrechtsprofessor"},{"wort":"Völkerrechtsprofessoren"},{"wort":"Völkerrechtsprofessorin"},{"wort":"Völkerrechtsprofessorinnen"},{"wort":"Völkerrechtsprofessur"},{"wort":"Völkerrechtsquelle"},{"wort":"Völkerrechtsquellen"},{"wort":"Völkerrechtssouveränität"},{"wort":"Völkerrechtssouveränitäten"},{"wort":"Völkerrechtsstudent"},{"wort":"Völkerrechtssubjekt"},{"wort":"Völkerrechtssubjekte"},{"wort":"Völkerrechtssubjekten"},{"wort":"Völkerrechtssubjektes"},{"wort":"Völkerrechtssubjektivität"},{"wort":"Völkerrechtssystem"},{"wort":"Völkerrechtssysteme"},{"wort":"Völkerrechtssystemen"},{"wort":"Völkerrechtssystems"},{"wort":"Völkerrechtsverbrechen"},{"wort":"Völkerrechtsverbrechens"},{"wort":"Völkerrechtsverletzung"},{"wort":"Völkerrechtsverletzungen"},{"wort":"Völkerrechtsvertrag"},{"wort":"Völkerrechtsverträge"},{"wort":"Völkerrechtsverträgen"},{"wort":"Völkerrechtsvertrages"},{"wort":"völkerrechtswidrig"},{"wort":"völkerrechtswidrige"},{"wort":"völkerrechtswidrigem"},{"wort":"völkerrechtswidrigen"},{"wort":"völkerrechtswidriger"},{"wort":"völkerrechtswidriges"},{"wort":"Völkerrechtswissenschaft"},{"wort":"Völkerrechtswissenschaften"},{"wort":"Völkerrechtswissenschaftler"},{"wort":"Völkerrechtswissenschaftlerin"},{"wort":"Völkerrechtswissenschaftlern"},{"wort":"Völkerrechtswissenschaftlers"},{"wort":"Völkerschaft"},{"wort":"Völkerschaften"},{"wort":"Völkerschar"},{"wort":"Völkerscharen"},{"wort":"Völkerschau"},{"wort":"Völkerschauen"},{"wort":"Völkerschlacht"},{"wort":"Völkerschlachtdenkmal"},{"wort":"Völkerschlachtdenkmals"},{"wort":"Völkerschlachten"},{"wort":"Völkersegen"},{"wort":"Völkersegens"},{"wort":"Völkersouveränität"},{"wort":"Völkersouveränitäten"},{"wort":"Völkerstamm"},{"wort":"Völkerstämme"},{"wort":"Völkerstämmen"},{"wort":"Völkerstammes"},{"wort":"Völkerstrafgesetzbuch"},{"wort":"Völkerstrafgesetzbücher"},{"wort":"Völkerstrafgesetzbüchern"},{"wort":"Völkerstrafgesetzbuches"},{"wort":"Völkerstrafgesetzbuchs"},{"wort":"Völkerstrafrecht"},{"wort":"Völkerstrafrechtes"},{"wort":"Völkerstrafrechts"},{"wort":"Völkerstrasse"},{"wort":"Völkerstrassen"},{"wort":"Völkersturm"},{"wort":"Völkersturms"},{"wort":"Völkertafel"},{"wort":"Völkertafeln"},{"wort":"Völkerteil"},{"wort":"Völkerteile"},{"wort":"Völkerteilen"},{"wort":"Völkerteils"},{"wort":"Völkertotschlag"},{"wort":"Völkertotschlages"},{"wort":"Völkertötung"},{"wort":"Völkertötungen"},{"wort":"Völkertrennung"},{"wort":"Völkertrennungen"},{"wort":"Völkerunion"},{"wort":"Völkerunionen"},{"wort":"Völkerunterscheidung"},{"wort":"Völkerunterscheidungen"},{"wort":"völkerverbindend"},{"wort":"völkerverbindende"},{"wort":"völkerverbindendem"},{"wort":"völkerverbindenden"},{"wort":"völkerverbindender"},{"wort":"völkerverbindendes"},{"wort":"Völkerverbrüderung"},{"wort":"Völkerverbrüderungen"},{"wort":"Völkerverheissung"},{"wort":"Völkerverheissungen"},{"wort":"Völkerverkehr"},{"wort":"Völkerverkehrs"},{"wort":"Völkervermischung"},{"wort":"Völkervermischungen"},{"wort":"Völkerverschiebung"},{"wort":"Völkerverschiebungen"},{"wort":"Völkerversöhnung"},{"wort":"Völkerversöhnungen"},{"wort":"Völkerverständigung"},{"wort":"Völkerverständigungen"},{"wort":"Völkerverständnis"},{"wort":"Völkerverständnisses"},{"wort":"Völkerverteilung"},{"wort":"Völkerverteilungen"},{"wort":"Völkervertragsrecht"},{"wort":"Völkervertragsrechte"},{"wort":"Völkervertragsrechten"},{"wort":"Völkervertragsrechtes"},{"wort":"Völkervertragsrechts"},{"wort":"Völkervertreibung"},{"wort":"Völkervertreibungen"},{"wort":"Völkerwallfahrt"},{"wort":"Völkerwallfahrten"},{"wort":"Völkerwanderschaft"},{"wort":"Völkerwanderschaften"},{"wort":"Völkerwanderung"},{"wort":"Völkerwanderungen"},{"wort":"Völkerwanderungszeit"},{"wort":"völkerwanderungszeitlich"},{"wort":"völkerwanderungszeitliche"},{"wort":"völkerwanderungszeitlichem"},{"wort":"völkerwanderungszeitlichen"},{"wort":"völkerwanderungszeitlicher"},{"wort":"völkerwanderungszeitliches"},{"wort":"Völkerweg"},{"wort":"Völkerwege"},{"wort":"Völkerwegen"},{"wort":"Völkerwelle"},{"wort":"Völkerwellen"},{"wort":"Völkerwelt"},{"wort":"Völkerwelten"},{"wort":"Völkerzerstörung"},{"wort":"Völkerzerstörungen"},{"wort":"völkisch"},{"wort":"völkische"},{"wort":"völkischem"},{"wort":"völkischen"},{"wort":"völkischer"},{"wort":"völkisches"},{"wort":"Völlegefühl"},{"wort":"Völlegefühle"},{"wort":"Völlegefühlen"},{"wort":"Völlegefühls"},{"wort":"Völler"},{"wort":"Völlerei"},{"wort":"völlig"},{"wort":"völlige"},{"wort":"völligem"},{"wort":"völligen"},{"wort":"völliger"},{"wort":"völliges"}]